{
  "posts": [
    {
      "book_name": "Screamer",
      "book_autor": "Snoxall",
      "genre": "firmware",
      "id": 9,
      "isSelected": false
    },
    {
      "id": 10,
      "book_name": "Tortoise, burmese brown mountain",
      "book_autor": "Sarene Beveredge",
      "genre": "collaboration",
      "isSelected": false
    },
    {
      "id": 11,
      "book_name": "Gecko, ring-tailed",
      "book_autor": "Mathias Dominique",
      "genre": "Expanded"
    },
    {
      "id": 12,
      "book_name": "Elephant, asian",
      "book_autor": "Cello Iddens",
      "genre": "Synergistic"
    },
    {
      "id": 13,
      "book_name": "Bonnet macaque",
      "book_autor": "Ingunna Paulley",
      "genre": "intranet"
    },
    {
      "id": 14,
      "book_name": "Vulture, white-rumped",
      "book_autor": "Anderson Blaisdell",
      "genre": "info-mediaries"
    },
    {
      "id": 15,
      "book_name": "Silver-backed jackal",
      "book_autor": "Stephana Staden",
      "genre": "Ameliorated"
    },
    {
      "id": 16,
      "book_name": "Swamp deer",
      "book_autor": "Tarra Couthard",
      "genre": "regional"
    },
    {
      "id": 17,
      "book_name": "Agouti",
      "book_autor": "Angeli Matzeitis",
      "genre": "internet solution"
    },
    {
      "id": 18,
      "book_name": "Owl, australian masked",
      "book_autor": "Renell Horstead",
      "genre": "capability"
    },
    {
      "id": 19,
      "book_name": "Spotted deer",
      "book_autor": "Linda Garn",
      "genre": "Expanded"
    },
    {
      "id": 20,
      "book_name": "Tern, arctic",
      "book_autor": "Freida Alyokhin",
      "genre": "benchmark"
    },
    {
      "id": 21,
      "book_name": "Penguin, magellanic",
      "book_autor": "Brant Margrett",
      "genre": "Compatible"
    },
    {
      "id": 22,
      "book_name": "Bee-eater (unidentified)",
      "book_autor": "Ashton Ollerenshaw",
      "genre": "uniform"
    },
    {
      "id": 23,
      "book_name": "Red lava crab",
      "book_autor": "Helena Janney",
      "genre": "forecast"
    },
    {
      "id": 24,
      "book_name": "Eleven-banded armadillo (unidentified)",
      "book_autor": "Keri Fassam",
      "genre": "Programmable"
    },
    {
      "id": 25,
      "book_name": "Kangaroo, jungle",
      "book_autor": "Courtenay Criple",
      "genre": "Integrated"
    },
    {
      "id": 26,
      "book_name": "Margay",
      "book_autor": "Lamar Jeannesson",
      "genre": "static"
    },
    {
      "id": 27,
      "book_name": "Trumpeter, green-winged",
      "book_autor": "Leslie Ebdon",
      "genre": "instruction set"
    },
    {
      "id": 28,
      "book_name": "Quoll, eastern",
      "book_autor": "Murray Blesdill",
      "genre": "Extended"
    },
    {
      "id": 29,
      "book_name": "Porcupine, tree",
      "book_autor": "Edwina Lucy",
      "genre": "initiative"
    },
    {
      "id": 30,
      "book_name": "Langur, hanuman",
      "book_autor": "Adrien Twiggins",
      "genre": "foreground"
    },
    {
      "id": 31,
      "book_name": "Pronghorn",
      "book_autor": "Baron Keegan",
      "genre": "Extended"
    },
    {
      "id": 32,
      "book_name": "Savannah deer",
      "book_autor": "Ham Belfrage",
      "genre": "clear-thinking"
    },
    {
      "id": 33,
      "book_name": "Green-winged macaw",
      "book_autor": "Freddi Ettles",
      "genre": "hybrid"
    },
    {
      "id": 34,
      "book_name": "Moorhen, purple",
      "book_autor": "Rodolfo Laverick",
      "genre": "leverage"
    },
    {
      "id": 35,
      "book_name": "Tasmanian devil",
      "book_autor": "Darcy Denmead",
      "genre": "Secured"
    },
    {
      "id": 36,
      "book_name": "Cliffchat, mocking",
      "book_autor": "Kessia Matoshin",
      "genre": "Robust"
    },
    {
      "id": 37,
      "book_name": "Goliath heron",
      "book_autor": "Lula Blaby",
      "genre": "contextually-based"
    },
    {
      "id": 38,
      "book_name": "Lion, asian",
      "book_autor": "Timmi Gollard",
      "genre": "heuristic"
    },
    {
      "id": 39,
      "book_name": "Magnificent frigate bird",
      "book_autor": "Shayna MacCallester",
      "genre": "Organic"
    },
    {
      "id": 40,
      "book_name": "Dove, rock",
      "book_autor": "Enriqueta Walthall",
      "genre": "Multi-channelled"
    },
    {
      "id": 41,
      "book_name": "Pie, indian tree",
      "book_autor": "Eda Coyle",
      "genre": "exuding"
    },
    {
      "id": 42,
      "book_name": "Bare-faced go away bird",
      "book_autor": "Fabien Manshaw",
      "genre": "system engine"
    },
    {
      "id": 43,
      "book_name": "Starling, cape",
      "book_autor": "Neely Tripett",
      "genre": "real-time"
    },
    {
      "id": 44,
      "book_name": "Galapagos dove",
      "book_autor": "Hewett Ivanyukov",
      "genre": "methodology"
    },
    {
      "id": 45,
      "book_name": "Red-billed buffalo weaver",
      "book_autor": "Bobette Secrett",
      "genre": "collaboration"
    },
    {
      "id": 46,
      "book_name": "Mouse, four-striped grass",
      "book_autor": "Julee Leavey",
      "genre": "function"
    },
    {
      "id": 47,
      "book_name": "American beaver",
      "book_autor": "Meg Moneti",
      "genre": "systematic"
    },
    {
      "id": 48,
      "book_name": "Hyrax",
      "book_autor": "Selestina Bulman",
      "genre": "analyzer"
    },
    {
      "id": 49,
      "book_name": "Seal, northern elephant",
      "book_autor": "Alisander Kurtis",
      "genre": "attitude-oriented"
    },
    {
      "id": 50,
      "book_name": "Adouri (unidentified)",
      "book_autor": "Gilbertina Benn",
      "genre": "Focused"
    }
  ]
}